camcli/__init__.py
camcli/client.py
camcli-0.0.1.dist-info/LICENSE
camcli-0.0.1.dist-info/METADATA
camcli-0.0.1.dist-info/WHEEL
camcli-0.0.1.dist-info/top_level.txt
camcli-0.0.1.dist-info/RECORD
