Metadata-Version: 2.1
Name: camcli
Version: 0.0.1
Summary: camcli
Home-page: https://github.com/iminders/camcli
Author: liuwen
Author-email: liuwen.w@qq.com
License: UNKNOWN
Platform: UNKNOWN
Classifier: Programming Language :: Python :: 3
Classifier: License :: OSI Approved :: MIT License
Classifier: Operating System :: OS Independent
Requires-Python: >=3
Requires-Dist: requests
Requires-Dist: pytest
